GoogleDrive/__init__.py
GoogleDrive/auth.py
GoogleDrive/drive.py
GoogleDriveWrapper-0.1.7.dist-info/LICENSE
GoogleDriveWrapper-0.1.7.dist-info/METADATA
GoogleDriveWrapper-0.1.7.dist-info/WHEEL
GoogleDriveWrapper-0.1.7.dist-info/top_level.txt
GoogleDriveWrapper-0.1.7.dist-info/RECORD
