Metadata-Version: 2.1
Name: GoogleDriveWrapper
Version: 0.1.7
Summary: A small package to make it easier work with GoogleDrive
Home-page: https://github.com/jpmarques-97
Author: João Paulo
Author-email: jpmarques@ufrn.edu.br
License: UNKNOWN
Project-URL: Bug Tracker, https://github.com/jpmarques-97
Platform: UNKNOWN
Classifier: Programming Language :: Python :: 3
Classifier: License :: OSI Approved :: MIT License
Classifier: Operating System :: OS Independent
Requires-Python: >=3.6
License-File: LICENSE
Requires-Dist: pandas
Requires-Dist: numpy
Requires-Dist: google-api-python-client
Requires-Dist: google-auth-httplib2
Requires-Dist: google-auth-oauthlib
Requires-Dist: oauth2client
Requires-Dist: httplib2
